cerbogen/__init__.py
cerbogen/main.py
cerbogen/data/img/logo.ico
cerbogen/data/img/logo.png
cerbogen/install/__init__.py
cerbogen/install/check.py
cerbogen/install/install.py
cerbogen/install/install_ffmpeg.py
cerbogen/install/install_location.py
cerbogen/mod/__init__.py
cerbogen/mod/cerbogen.py
cerbogen/mod/plot.py
cerbogen-0.0.55.dist-info/METADATA
cerbogen-0.0.55.dist-info/WHEEL
cerbogen-0.0.55.dist-info/top_level.txt
cerbogen-0.0.55.dist-info/RECORD
